setup.py
demo/__init__.py
demo/app.py
demo/test_0_101.py
opsapp/__init__.py
opsapp.egg-info/PKG-INFO
opsapp.egg-info/SOURCES.txt
opsapp.egg-info/dependency_links.txt
opsapp.egg-info/requires.txt
opsapp.egg-info/top_level.txt
opsapp/app/__init__.py
opsapp/app/main.py
opsapp/app/core/__init__.py
opsapp/app/core/aip/__init__.py
opsapp/app/core/events/__init__.py
opsapp/app/core/events/events.py
opsapp/app/core/logging/__init__.py
opsapp/app/core/logging/logging.py
opsapp/app/core/middleware/__init__.py
opsapp/app/core/middleware/middleware.py
opsapp/app/core/openapi/__init__.py
opsapp/app/core/openapi/converter.py
opsapp/app/core/redis/__init__.py
opsapp/app/core/redis/redis.py
opsapp/app/core/response/BaseResponse.py
opsapp/app/core/response/__init__.py
opsapp/app/core/response/http_error.py
opsapp/app/core/response/validation_error.py
opsapp/app/core/router/__init__.py
opsapp/app/core/router/router.py
opsapp/app/core/utils/__init__.py
opsapp/app/core/utils/utils.py
opsapp/app/core/websocket/__init__.py
opsapp/app/core/websocket/websocket.py
opsapp/app/models/__init__.py
opsapp/app/models/db.py
opsapp/app/settings/__init__.py
opsapp/app/settings/config.py
opsapp/app/swagger/__init__.py
opsapp/app/swagger/redoc.standalone.js
opsapp/app/swagger/redoc.standalone.js.map
opsapp/app/swagger/swagger-ui-bundle.js
opsapp/app/swagger/swagger-ui-bundle.js.map
opsapp/app/swagger/swagger-ui.css
opsapp/app/swagger/swagger-ui.css.map
opsapp/base/__init__.py
opsapp/base/hook.py
opsapp/base/logger.py
opsapp/base/misc.py
opsapp/base/path.py
opsapp/base/progressbar.py
opsapp/base/registry.py
opsapp/base/timer.py
opsapp/utils/__init__.py
opsapp/utils/base64utils.py
opsapp/utils/colors.py
opsapp/utils/utils.py
opsapp/utils/visualization.py
test/test.py
test/test2.py