Metadata-Version: 2.1
Name: opsapp
Version: 0.0.31
Summary: This is the ml opsapp
Home-page: https://gitee.com/zhys513/opsapp
Author: zhys513
Author-email: 254851907@qq.com
License: UNKNOWN
Platform: UNKNOWN
Requires-Python: >=3.6
